daniel_zindi_utils/__init__.py
daniel_zindi_utils/chrf.py
daniel_zindi_utils/utils.py
daniel_zindi_utils-0.3.0.dist-info/METADATA
daniel_zindi_utils-0.3.0.dist-info/WHEEL
daniel_zindi_utils-0.3.0.dist-info/top_level.txt
daniel_zindi_utils-0.3.0.dist-info/RECORD
