Metadata-Version: 2.1
Name: daniel-zindi-utils
Version: 0.3.0
Summary: UNKNOWN
Home-page: UNKNOWN
Author: Daniel Byiringiro
Author-email: daniel.byiringiro@ashesi.edu.gh
License: UNKNOWN
Platform: UNKNOWN
Requires-Dist: datasets
Requires-Dist: numpy
Requires-Dist: pandas
